{"uuid": "c1eef542-a4e3-454e-9fee-564eb7b7d123", "name": "Untitled-c1eef542", "type": "Table", "authorEmail": "johnkim@applied.co", "rawConfigJsonProto": {"chartConfigs": [{"uuid": "c1eef542-a4e3-454e-9fee-564eb7b7d123", "name": "Untitled-c1eef542", "nonce": "3caaba04-d772-4e73-af7e-4d80975d7eaa", "chartConfig": {"type": "Table", "colorsJson": "[]", "queryConfig": {"value": "SELECT 2", "rowLimit": 1000, "uuid": "8d47fd6f-312f-4c14-a8d9-564a65eaceab"}, "protoVersion": "V2_0", "tableConfig": {}}, "version": 1, "ownerEmail": "johnkim@applied.co"}]}, "source": 1}
